poe.py
poe/__init__.py
poe/hashes.py
poe/poe_graphql/AddHumanMessageMutation.graphql
poe/poe_graphql/AddMessageBreakMutation.graphql
poe/poe_graphql/AutoSubscriptionMutation.graphql
poe/poe_graphql/BioFragment.graphql
poe/poe_graphql/ChatAddedSubscription.graphql
poe/poe_graphql/ChatFragment.graphql
poe/poe_graphql/ChatListPaginationQuery.graphql
poe/poe_graphql/ChatPaginationQuery.graphql
poe/poe_graphql/ChatViewQuery.graphql
poe/poe_graphql/DeleteHumanMessagesMutation.graphql
poe/poe_graphql/DeleteMessageMutation.graphql
poe/poe_graphql/DeleteUserMessagesMutation.graphql
poe/poe_graphql/ExploreBotsListPaginationQuery.graphql
poe/poe_graphql/HandleFragment.graphql
poe/poe_graphql/LoginWithVerificationCodeMutation.graphql
poe/poe_graphql/MessageAddedSubscription.graphql
poe/poe_graphql/MessageDeletedSubscription.graphql
poe/poe_graphql/MessageFragment.graphql
poe/poe_graphql/MessageRemoveVoteMutation.graphql
poe/poe_graphql/MessageSetVoteMutation.graphql
poe/poe_graphql/PoeBotCreateMutation.graphql
poe/poe_graphql/PoeBotEditMutation.graphql
poe/poe_graphql/SendMessageMutation.graphql
poe/poe_graphql/SendVerificationCodeForLoginMutation.graphql
poe/poe_graphql/ShareMessagesMutation.graphql
poe/poe_graphql/SignupWithVerificationCodeMutation.graphql
poe/poe_graphql/StaleChatUpdateMutation.graphql
poe/poe_graphql/SubscriptionsMutation.graphql
poe/poe_graphql/SummarizePlainPostQuery.graphql
poe/poe_graphql/SummarizeQuotePostQuery.graphql
poe/poe_graphql/SummarizeSharePostQuery.graphql
poe/poe_graphql/UserSnippetFragment.graphql
poe/poe_graphql/ViewerInfoQuery.graphql
poe/poe_graphql/ViewerStateFragment.graphql
poe/poe_graphql/ViewerStateUpdatedSubscription.graphql
poe/poe_graphql/queries.json
poe_graphql/AddHumanMessageMutation.graphql
poe_graphql/AddMessageBreakMutation.graphql
poe_graphql/AutoSubscriptionMutation.graphql
poe_graphql/BioFragment.graphql
poe_graphql/ChatAddedSubscription.graphql
poe_graphql/ChatFragment.graphql
poe_api-0.5.3.dist-info/LICENSE
poe_api-0.5.3.dist-info/METADATA
poe_api-0.5.3.dist-info/WHEEL
poe_api-0.5.3.dist-info/top_level.txt
poe_api-0.5.3.dist-info/RECORD
