Metadata-Version: 2.1
Name: poe-api
Version: 0.5.3
Summary: A reverse engineered API wrapper for Quora's Poe
Home-page: https://github.com/ading2210/poe-api
Author: ading2210
License: GPLv3
Classifier: Programming Language :: Python :: 3
Classifier: License :: OSI Approved :: GNU General Public License (GPL)
Classifier: Operating System :: OS Independent
Requires-Python: >=3.7
License-File: LICENSE
Requires-Dist: brotlicffi
Requires-Dist: httpx
Requires-Dist: quickjs
Requires-Dist: tls-client
Requires-Dist: websocket-client
